lantern_pinecone/__init__.py
lantern_pinecone/client.py
lantern_pinecone/setup.py
lantern_pinecone-0.0.8.dist-info/LICENSE
lantern_pinecone-0.0.8.dist-info/METADATA
lantern_pinecone-0.0.8.dist-info/WHEEL
lantern_pinecone-0.0.8.dist-info/top_level.txt
lantern_pinecone-0.0.8.dist-info/RECORD
