Metadata-Version: 2.1
Name: lantern-pinecone
Version: 0.0.8
Summary: Pinecone compatiable client for Lantern
Home-page: https://github.com/lanterndata/lantern-python
Author: Varik Matevosyan
Author-email: varik@lantern.dev
License: MIT
Project-URL: Bug Tracker, https://github.com/lanterndata/lantern-python/issues
Classifier: Programming Language :: Python :: 3
Classifier: License :: OSI Approved :: MIT License
Classifier: Operating System :: OS Independent
Requires-Python: >=3.8
License-File: LICENSE
Requires-Dist: lantern-client ==0.0.6
Requires-Dist: tqdm >=4.66.3
Requires-Dist: pinecone-client ==2.2.4
